pyqai/__init__.py
pyqai/deploy.py
pyqai/deployments.py
pyqai/init.py
pyqai/logs.py
pyqai/pods.py
pyqai-0.5.5.dist-info/LICENSE
pyqai-0.5.5.dist-info/METADATA
pyqai-0.5.5.dist-info/WHEEL
pyqai-0.5.5.dist-info/entry_points.txt
pyqai-0.5.5.dist-info/top_level.txt
pyqai-0.5.5.dist-info/RECORD
