Metadata-Version: 2.1
Name: pyqai
Version: 0.5.5
Summary: The pyq MLOps package
Author-email: Emily Dorsey <emily@pyqai.com>, Aman Raghuvanshi <aman@pyqai.com>
License: Copyright (c) 2018 The Python Packaging Authority
Project-URL: Homepage, https://www.pyqai.com
Classifier: Programming Language :: Python :: 3
Classifier: License :: OSI Approved :: MIT License
Classifier: Operating System :: OS Independent
Requires-Python: >=3.7
License-File: LICENSE
Requires-Dist: docker
Requires-Dist: kubernetes
Requires-Dist: protobuf
Requires-Dist: PyYAML
Requires-Dist: requests
Requires-Dist: pipreqs
